llmkit/__init__.py
llmkit/config.py
llmkit/main.py
llmkit/models/__init__.py
llmkit/models/generics.py
llmkit/models/prompt.py
llmkit/services/__init__.py
llmkit/services/exceptions.py
llmkit/services/inference.py
llmkit/services/model.py
llmkit/transformers/__init__.py
llmkit/transformers/base.py
llmkit/transformers/default.py
llm_stack_kit-0.1.5.dist-info/LICENSE
llm_stack_kit-0.1.5.dist-info/METADATA
llm_stack_kit-0.1.5.dist-info/WHEEL
llm_stack_kit-0.1.5.dist-info/RECORD
