Metadata-Version: 2.1
Name: llm-stack-kit
Version: 0.1.5
Summary: Generate Data from LLM easily using LLMKit
Home-page: https://github.com/useentropy/llmkit
Author: Tosin Amuda
Author-email: tosinamuda@gmail.com
Requires-Python: >=3.8.1,<4.0.0
Classifier: Programming Language :: Python :: 3
Classifier: Programming Language :: Python :: 3.9
Classifier: Programming Language :: Python :: 3.10
Classifier: Programming Language :: Python :: 3.11
Requires-Dist: openai (>=0.28.1,<0.29.0)
Requires-Dist: pydantic (>=2.4.2,<3.0.0)
Requires-Dist: python-dotenv (>=1.0.0,<2.0.0)
Project-URL: Repository, https://github.com/useentropy/llmkit
